{
    "name": "아르망 드 브리냑 브뤼 골드",
    "en_name": "Armand de Brignac Brut Gold",
    "flavor description": "전통 샴페인의 진수를 보여주는 와인 전통의 표상을 담은 현대의 프레스티지 퀴베 아르망 드 브리냑 브룻 골드는 아르망 드 브리냑의 포트폴리오에 처음으로 출시된 퀴베이자 브랜드를 대표할 플래그십 샴페인입니다. 까띠에르 가문은 샹파뉴 지방의 풍성한 와인메이킹 전통을 반영하면서도 21세기에 걸맞은 최고의 프레스티지 퀴베를 탄생시키겠다는 포부를 품었습니다. 그렇기에 다양한 빈티지, 떼루아, 포도 품종의 노련한 배합이야말로 아르망 드 브리냑이 가진 철학의 본질이라 할 수 있습니다.",
    "pairing": "아페리티프 구운 관자 요리 메추리 구이 민물생선 요리",
    "product info": "생산자,아르망 드 브리냑(Armand de Brignac),국가/지역,프랑스/샹파뉴,스타일,스파클링와인,용량,750mL"
}