{"version":"V2","requestId":"84f07716-3b65-4bec-ba3a-29af6dbd8466","timestamp":1688219109277,"images":[{"uid":"879ad9752fea406e923a5b52d3afdafb","name":"demo","inferResult":"SUCCESS","message":"SUCCESS","validationResult":{"result":"NO_REQUESTED"},"convertedImageInfo":{"width":1000,"height":4655,"pageIndex":0,"longImage":false},"fields":[{"valueType":"ALL","boundingPoly":{"vertices":[{"x":254.0,"y":133.0},{"x":432.0,"y":133.0},{"x":432.0,"y":212.0},{"x":254.0,"y":212.0}]},"inferText":"코디치","inferConfidence":0.9997,"type":"NORMAL","lineBreak":false},{"valueType":"ALL","boundingPoly":{"vertices":[{"x":441.0,"y":133.0},{"x":561.0,"y":133.0},{"x":561.0,"y":200.0},{"x":441.0,"y":200.0}]},"inferText":"로쏘","inferConfidence":0.9998,"type":"NORMAL","lineBreak":false},{"valueType":"ALL","boundingPoly":{"vertices":[{"x":565.0,"y":133.0},{"x":748.0,"y":133.0},{"x":748.0,"y":208.0},{"x":565.0,"y":208.0}]},"inferText":"스위트","inferConfidence":0.9998,"type":"NORMAL","lineBreak":true},{"valueType":"ALL","boundingPoly":{"vertices":[{"x":308.0,"y":220.0},{"x":445.0,"y":220.0},{"x":445.0,"y":274.0},{"x":308.0,"y":274.0}]},"inferText":"Codici","inferConfidence":0.9996,"type":"NORMAL","lineBreak":false},{"valueType":"ALL","boundingPoly":{"vertices":[{"x":436.0,"y":224.0},{"x":569.0,"y":224.0},{"x":569.0,"y":278.0},{"x":436.0,"y":278.0}]},"inferText":"Rosso","inferConfidence":1.0,"type":"NORMAL","lineBreak":false},{"valueType":"ALL","boundingPoly":{"vertices":[{"x":561.0,"y":224.0},{"x":698.0,"y":224.0},{"x":698.0,"y":274.0},{"x":561.0,"y":274.0}]},"inferText":"Sweet","inferConfidence":1.0,"type":"NORMAL","lineBreak":true},{"valueType":"ALL","boundingPoly":{"vertices":[{"x":436.0,"y":765.0},{"x":574.0,"y":765.0},{"x":574.0,"y":819.0},{"x":436.0,"y":819.0}]},"inferText":"CODICI","inferConfidence":0.8847,"type":"NORMAL","lineBreak":true},{"valueType":"ALL","boundingPoly":{"vertices":[{"x":449.0,"y":869.0},{"x":565.0,"y":869.0},{"x":565.0,"y":894.0},{"x":449.0,"y":894.0}]},"inferText":"VINO ROSSO","inferConfidence":0.9997,"type":"NORMAL","lineBreak":true},{"valueType":"ALL","boundingPoly":{"vertices":[{"x":262.0,"y":1330.0},{"x":470.0,"y":1330.0},{"x":470.0,"y":1401.0},{"x":262.0,"y":1401.0}]},"inferText":"1시간마다","inferConfidence":1.0,"type":"NORMAL","lineBreak":false},{"valueType":"ALL","boundingPoly":{"vertices":[{"x":457.0,"y":1330.0},{"x":607.0,"y":1330.0},{"x":607.0,"y":1401.0},{"x":457.0,"y":1401.0}]},"inferText":"10병씩","inferConfidence":0.9999,"type":"NORMAL","lineBreak":false},{"valueType":"ALL","boundingPoly":{"vertices":[{"x":598.0,"y":1330.0},{"x":736.0,"y":1330.0},{"x":736.0,"y":1401.0},{"x":598.0,"y":1401.0}]},"inferText":"팔리는","inferConfidence":0.9986,"type":"NORMAL","lineBreak":true},{"valueType":"ALL","boundingPoly":{"vertices":[{"x":191.0,"y":1401.0},{"x":341.0,"y":1401.0},{"x":341.0,"y":1463.0},{"x":191.0,"y":1463.0}]},"inferText":"달콤한","inferConfidence":0.9995,"type":"NORMAL","lineBreak":false},{"valueType":"ALL","boundingPoly":{"vertices":[{"x":341.0,"y":1401.0},{"x":594.0,"y":1401.0},{"x":594.0,"y":1471.0},{"x":341.0,"y":1471.0}]},"inferText":"베스트셀링","inferConfidence":1.0,"type":"NORMAL","lineBreak":false},{"valueType":"ALL","boundingPoly":{"vertices":[{"x":594.0,"y":1401.0},{"x":790.0,"y":1401.0},{"x":790.0,"y":1467.0},{"x":594.0,"y":1467.0}]},"inferText":"레드와인","inferConfidence":0.9999,"type":"NORMAL","lineBreak":true},{"valueType":"ALL","boundingPoly":{"vertices":[{"x":216.0,"y":1654.0},{"x":362.0,"y":1654.0},{"x":362.0,"y":1704.0},{"x":216.0,"y":1704.0}]},"inferText":"1시간마다","inferConfidence":1.0,"type":"NORMAL","lineBreak":false},{"valueType":"ALL","boundingPoly":{"vertices":[{"x":349.0,"y":1654.0},{"x":457.0,"y":1654.0},{"x":457.0,"y":1704.0},{"x":349.0,"y":1704.0}]},"inferText":"10병씩","inferConfidence":0.9999,"type":"NORMAL","lineBreak":false},{"valueType":"ALL","boundingPoly":{"vertices":[{"x":449.0,"y":1654.0},{"x":549.0,"y":1654.0},{"x":549.0,"y":1704.0},{"x":449.0,"y":1704.0}]},"inferText":"팔리는","inferConfidence":0.9989,"type":"NORMAL","lineBreak":false},{"valueType":"ALL","boundingPoly":{"vertices":[{"x":540.0,"y":1654.0},{"x":636.0,"y":1654.0},{"x":636.0,"y":1704.0},{"x":540.0,"y":1704.0}]},"inferText":"달콤한","inferConfidence":0.998,"type":"NORMAL","lineBreak":false},{"valueType":"ALL","boundingPoly":{"vertices":[{"x":628.0,"y":1654.0},{"x":781.0,"y":1654.0},{"x":781.0,"y":1704.0},{"x":628.0,"y":1704.0}]},"inferText":"베스트셀링","inferConfidence":1.0,"type":"NORMAL","lineBreak":true},{"valueType":"ALL","boundingPoly":{"vertices":[{"x":150.0,"y":1712.0},{"x":245.0,"y":1712.0},{"x":245.0,"y":1750.0},{"x":150.0,"y":1750.0}]},"inferText":"스위트","inferConfidence":0.9997,"type":"NORMAL","lineBreak":false},{"valueType":"ALL","boundingPoly":{"vertices":[{"x":237.0,"y":1708.0},{"x":362.0,"y":1708.0},{"x":362.0,"y":1754.0},{"x":237.0,"y":1754.0}]},"inferText":"레드와인","inferConfidence":1.0,"type":"NORMAL","lineBreak":false},{"valueType":"ALL","boundingPoly":{"vertices":[{"x":353.0,"y":1708.0},{"x":453.0,"y":1708.0},{"x":453.0,"y":1758.0},{"x":353.0,"y":1758.0}]},"inferText":"풍부한","inferConfidence":0.9994,"type":"NORMAL","lineBreak":false},{"valueType":"ALL","boundingPoly":{"vertices":[{"x":445.0,"y":1708.0},{"x":520.0,"y":1708.0},{"x":520.0,"y":1758.0},{"x":445.0,"y":1758.0}]},"inferText":"과실","inferConfidence":0.9999,"type":"NORMAL","lineBreak":false},{"valueType":"ALL","boundingPoly":{"vertices":[{"x":507.0,"y":1708.0},{"x":561.0,"y":1708.0},{"x":561.0,"y":1758.0},{"x":507.0,"y":1758.0}]},"inferText":"향,","inferConfidence":1.0,"type":"NORMAL","lineBreak":false},{"valueType":"ALL","boundingPoly":{"vertices":[{"x":549.0,"y":1708.0},{"x":707.0,"y":1708.0},{"x":707.0,"y":1758.0},{"x":549.0,"y":1758.0}]},"inferText":"라즈베리와","inferConfidence":1.0,"type":"NORMAL","lineBreak":false},{"valueType":"ALL","boundingPoly":{"vertices":[{"x":694.0,"y":1708.0},{"x":848.0,"y":1708.0},{"x":848.0,"y":1758.0},{"x":694.0,"y":1758.0}]},"inferText":"블랙베리의","inferConfidence":0.9999,"type":"NORMAL","lineBreak":true},{"valueType":"ALL","boundingPoly":{"vertices":[{"x":204.0,"y":1758.0},{"x":278.0,"y":1758.0},{"x":278.0,"y":1808.0},{"x":204.0,"y":1808.0}]},"inferText":"향을","inferConfidence":1.0,"type":"NORMAL","lineBreak":false},{"valueType":"ALL","boundingPoly":{"vertices":[{"x":266.0,"y":1758.0},{"x":370.0,"y":1758.0},{"x":370.0,"y":1808.0},{"x":266.0,"y":1808.0}]},"inferText":"가졌고","inferConfidence":0.9998,"type":"NORMAL","lineBreak":false},{"valueType":"ALL","boundingPoly":{"vertices":[{"x":357.0,"y":1758.0},{"x":432.0,"y":1758.0},{"x":432.0,"y":1808.0},{"x":357.0,"y":1808.0}]},"inferText":"진한","inferConfidence":0.9999,"type":"NORMAL","lineBreak":false},{"valueType":"ALL","boundingPoly":{"vertices":[{"x":424.0,"y":1758.0},{"x":495.0,"y":1758.0},{"x":495.0,"y":1808.0},{"x":424.0,"y":1808.0}]},"inferText":"보라","inferConfidence":0.9994,"type":"NORMAL","lineBreak":false},{"valueType":"ALL","boundingPoly":{"vertices":[{"x":482.0,"y":1758.0},{"x":557.0,"y":1758.0},{"x":557.0,"y":1808.0},{"x":482.0,"y":1808.0}]},"inferText":"빛이","inferConfidence":1.0,"type":"NORMAL","lineBreak":false},{"valueType":"ALL","boundingPoly":{"vertices":[{"x":544.0,"y":1758.0},{"x":648.0,"y":1758.0},{"x":648.0,"y":1808.0},{"x":544.0,"y":1808.0}]},"inferText":"감도는","inferConfidence":0.9999,"type":"NORMAL","lineBreak":false},{"valueType":"ALL","boundingPoly":{"vertices":[{"x":636.0,"y":1758.0},{"x":790.0,"y":1758.0},{"x":790.0,"y":1808.0},{"x":636.0,"y":1808.0}]},"inferText":"달콤하면서","inferConfidence":0.9994,"type":"NORMAL","lineBreak":true},{"valueType":"ALL","boundingPoly":{"vertices":[{"x":312.0,"y":1812.0},{"x":441.0,"y":1812.0},{"x":441.0,"y":1862.0},{"x":312.0,"y":1862.0}]},"inferText":"감미로운","inferConfidence":0.9999,"type":"NORMAL","lineBreak":false},{"valueType":"ALL","boundingPoly":{"vertices":[{"x":432.0,"y":1812.0},{"x":532.0,"y":1812.0},{"x":532.0,"y":1862.0},{"x":432.0,"y":1862.0}]},"inferText":"이태리","inferConfidence":1.0,"type":"NORMAL","lineBreak":false},{"valueType":"ALL","boundingPoly":{"vertices":[{"x":520.0,"y":1812.0},{"x":623.0,"y":1812.0},{"x":623.0,"y":1862.0},{"x":520.0,"y":1862.0}]},"inferText":"디저트","inferConfidence":0.9997,"type":"NORMAL","lineBreak":false},{"valueType":"ALL","boundingPoly":{"vertices":[{"x":611.0,"y":1812.0},{"x":686.0,"y":1812.0},{"x":686.0,"y":1862.0},{"x":611.0,"y":1862.0}]},"inferText":"와인","inferConfidence":0.9999,"type":"NORMAL","lineBreak":true},{"valueType":"ALL","boundingPoly":{"vertices":[{"x":308.0,"y":2282.0},{"x":553.0,"y":2282.0},{"x":553.0,"y":2352.0},{"x":308.0,"y":2352.0}]},"inferText":"Product","inferConfidence":0.9996,"type":"NORMAL","lineBreak":false},{"valueType":"ALL","boundingPoly":{"vertices":[{"x":549.0,"y":2282.0},{"x":686.0,"y":2282.0},{"x":686.0,"y":2352.0},{"x":549.0,"y":2352.0}]},"inferText":"Info","inferConfidence":0.9928,"type":"NORMAL","lineBreak":true},{"valueType":"ALL","boundingPoly":{"vertices":[{"x":166.0,"y":2498.0},{"x":262.0,"y":2498.0},{"x":262.0,"y":2548.0},{"x":166.0,"y":2548.0}]},"inferText":"생산자","inferConfidence":1.0,"type":"NORMAL","lineBreak":false},{"valueType":"ALL","boundingPoly":{"vertices":[{"x":353.0,"y":2498.0},{"x":495.0,"y":2498.0},{"x":495.0,"y":2544.0},{"x":353.0,"y":2544.0}]},"inferText":"몬도델비노","inferConfidence":0.9996,"type":"NORMAL","lineBreak":true},{"valueType":"ALL","boundingPoly":{"vertices":[{"x":145.0,"y":2610.0},{"x":283.0,"y":2610.0},{"x":283.0,"y":2660.0},{"x":145.0,"y":2660.0}]},"inferText":"국가/지역","inferConfidence":0.9999,"type":"NORMAL","lineBreak":false},{"valueType":"ALL","boundingPoly":{"vertices":[{"x":353.0,"y":2610.0},{"x":449.0,"y":2610.0},{"x":449.0,"y":2660.0},{"x":353.0,"y":2660.0}]},"inferText":"이태리","inferConfidence":1.0,"type":"NORMAL","lineBreak":false},{"valueType":"ALL","boundingPoly":{"vertices":[{"x":445.0,"y":2623.0},{"x":466.0,"y":2623.0},{"x":466.0,"y":2648.0},{"x":445.0,"y":2648.0}]},"inferText":"/","inferConfidence":0.9998,"type":"NORMAL","lineBreak":false},{"valueType":"ALL","boundingPoly":{"vertices":[{"x":461.0,"y":2610.0},{"x":557.0,"y":2610.0},{"x":557.0,"y":2660.0},{"x":461.0,"y":2660.0}]},"inferText":"풀리아","inferConfidence":1.0,"type":"NORMAL","lineBreak":true},{"valueType":"ALL","boundingPoly":{"vertices":[{"x":166.0,"y":2722.0},{"x":262.0,"y":2722.0},{"x":262.0,"y":2772.0},{"x":166.0,"y":2772.0}]},"inferText":"스타일","inferConfidence":0.9999,"type":"NORMAL","lineBreak":false},{"valueType":"ALL","boundingPoly":{"vertices":[{"x":353.0,"y":2722.0},{"x":507.0,"y":2722.0},{"x":507.0,"y":2772.0},{"x":353.0,"y":2772.0}]},"inferText":"산지오베제,","inferConfidence":1.0,"type":"NORMAL","lineBreak":false},{"valueType":"ALL","boundingPoly":{"vertices":[{"x":499.0,"y":2722.0},{"x":648.0,"y":2722.0},{"x":648.0,"y":2772.0},{"x":499.0,"y":2772.0}]},"inferText":"몬테풀차노,","inferConfidence":0.9998,"type":"NORMAL","lineBreak":false},{"valueType":"ALL","boundingPoly":{"vertices":[{"x":644.0,"y":2722.0},{"x":823.0,"y":2722.0},{"x":823.0,"y":2772.0},{"x":644.0,"y":2772.0}]},"inferText":"네그로아마로,","inferConfidence":0.9998,"type":"NORMAL","lineBreak":false},{"valueType":"ALL","boundingPoly":{"vertices":[{"x":810.0,"y":2722.0},{"x":906.0,"y":2722.0},{"x":906.0,"y":2768.0},{"x":810.0,"y":2768.0}]},"inferText":"메를로","inferConfidence":0.9999,"type":"NORMAL","lineBreak":true},{"valueType":"ALL","boundingPoly":{"vertices":[{"x":183.0,"y":2839.0},{"x":245.0,"y":2839.0},{"x":245.0,"y":2876.0},{"x":183.0,"y":2876.0}]},"inferText":"용량","inferConfidence":0.9999,"type":"NORMAL","lineBreak":false},{"valueType":"ALL","boundingPoly":{"vertices":[{"x":353.0,"y":2839.0},{"x":453.0,"y":2839.0},{"x":453.0,"y":2876.0},{"x":353.0,"y":2876.0}]},"inferText":"750ml","inferConfidence":0.9997,"type":"NORMAL","lineBreak":true},{"valueType":"ALL","boundingPoly":{"vertices":[{"x":300.0,"y":3253.0},{"x":514.0,"y":3266.0},{"x":510.0,"y":3327.0},{"x":297.0,"y":3315.0}]},"inferText":"Tasting","inferConfidence":1.0,"type":"NORMAL","lineBreak":false},{"valueType":"ALL","boundingPoly":{"vertices":[{"x":515.0,"y":3254.0},{"x":707.0,"y":3254.0},{"x":707.0,"y":3325.0},{"x":515.0,"y":3325.0}]},"inferText":"Notes","inferConfidence":0.9998,"type":"NORMAL","lineBreak":true},{"valueType":"ALL","boundingPoly":{"vertices":[{"x":108.0,"y":3491.0},{"x":166.0,"y":3491.0},{"x":166.0,"y":3529.0},{"x":108.0,"y":3529.0}]},"inferText":"당도","inferConfidence":0.9999,"type":"NORMAL","lineBreak":true},{"valueType":"ALL","boundingPoly":{"vertices":[{"x":108.0,"y":3624.0},{"x":166.0,"y":3624.0},{"x":166.0,"y":3662.0},{"x":108.0,"y":3662.0}]},"inferText":"산도","inferConfidence":0.9999,"type":"NORMAL","lineBreak":true},{"valueType":"ALL","boundingPoly":{"vertices":[{"x":108.0,"y":3761.0},{"x":166.0,"y":3761.0},{"x":166.0,"y":3795.0},{"x":108.0,"y":3795.0}]},"inferText":"바디","inferConfidence":0.9999,"type":"NORMAL","lineBreak":true},{"valueType":"ALL","boundingPoly":{"vertices":[{"x":466.0,"y":4027.0},{"x":536.0,"y":4027.0},{"x":536.0,"y":4115.0},{"x":466.0,"y":4115.0}]},"inferText":"iT","inferConfidence":0.3997,"type":"NORMAL","lineBreak":true},{"valueType":"ALL","boundingPoly":{"vertices":[{"x":291.0,"y":4127.0},{"x":457.0,"y":4127.0},{"x":457.0,"y":4198.0},{"x":291.0,"y":4198.0}]},"inferText":"Food","inferConfidence":0.9996,"type":"NORMAL","lineBreak":false},{"valueType":"ALL","boundingPoly":{"vertices":[{"x":467.0,"y":4123.0},{"x":705.0,"y":4142.0},{"x":701.0,"y":4204.0},{"x":462.0,"y":4185.0}]},"inferText":"Pairings","inferConfidence":0.9994,"type":"NORMAL","lineBreak":true},{"valueType":"ALL","boundingPoly":{"vertices":[{"x":150.0,"y":4514.0},{"x":245.0,"y":4514.0},{"x":245.0,"y":4559.0},{"x":150.0,"y":4559.0}]},"inferText":"달콤한","inferConfidence":0.9996,"type":"NORMAL","lineBreak":false},{"valueType":"ALL","boundingPoly":{"vertices":[{"x":241.0,"y":4514.0},{"x":316.0,"y":4514.0},{"x":316.0,"y":4564.0},{"x":241.0,"y":4564.0}]},"inferText":"케익","inferConfidence":0.9999,"type":"NORMAL","lineBreak":false},{"valueType":"ALL","boundingPoly":{"vertices":[{"x":466.0,"y":4518.0},{"x":528.0,"y":4518.0},{"x":528.0,"y":4555.0},{"x":466.0,"y":4555.0}]},"inferText":"치즈","inferConfidence":1.0,"type":"NORMAL","lineBreak":false},{"valueType":"ALL","boundingPoly":{"vertices":[{"x":732.0,"y":4514.0},{"x":802.0,"y":4514.0},{"x":802.0,"y":4559.0},{"x":732.0,"y":4559.0}]},"inferText":"과일","inferConfidence":0.9964,"type":"NORMAL","lineBreak":true}]}]}