{"version":"V2","requestId":"5d54cb85-bde1-4859-9e28-fb6ca4f00a7c","timestamp":1688194559903,"images":[{"uid":"a0bb6bc7b255424ea91ede85d05dfe5f","name":"demo","inferResult":"SUCCESS","message":"SUCCESS","validationResult":{"result":"NO_REQUESTED"},"convertedImageInfo":{"width":1080,"height":1648,"pageIndex":0,"longImage":false},"fields":[{"valueType":"ALL","boundingPoly":{"vertices":[{"x":131.0,"y":54.0},{"x":184.0,"y":54.0},{"x":184.0,"y":93.0},{"x":131.0,"y":93.0}]},"inferText":"\"","inferConfidence":0.9334,"type":"NORMAL","lineBreak":true},{"valueType":"ALL","boundingPoly":{"vertices":[{"x":234.0,"y":93.0},{"x":408.0,"y":93.0},{"x":408.0,"y":149.0},{"x":234.0,"y":149.0}]},"inferText":"감귤류와","inferConfidence":1.0,"type":"NORMAL","lineBreak":false},{"valueType":"ALL","boundingPoly":{"vertices":[{"x":409.0,"y":93.0},{"x":541.0,"y":93.0},{"x":541.0,"y":149.0},{"x":409.0,"y":149.0}]},"inferText":"핵과류","inferConfidence":0.9999,"type":"NORMAL","lineBreak":false},{"valueType":"ALL","boundingPoly":{"vertices":[{"x":541.0,"y":93.0},{"x":672.0,"y":93.0},{"x":672.0,"y":149.0},{"x":541.0,"y":149.0}]},"inferText":"풍미가","inferConfidence":1.0,"type":"NORMAL","lineBreak":false},{"valueType":"ALL","boundingPoly":{"vertices":[{"x":674.0,"y":93.0},{"x":842.0,"y":93.0},{"x":842.0,"y":149.0},{"x":674.0,"y":149.0}]},"inferText":"감미로운","inferConfidence":0.9998,"type":"NORMAL","lineBreak":true},{"valueType":"ALL","boundingPoly":{"vertices":[{"x":258.0,"y":157.0},{"x":592.0,"y":157.0},{"x":592.0,"y":230.0},{"x":258.0,"y":230.0}]},"inferText":"클라우드 베이","inferConfidence":0.9996,"type":"NORMAL","lineBreak":false},{"valueType":"ALL","boundingPoly":{"vertices":[{"x":594.0,"y":157.0},{"x":815.0,"y":157.0},{"x":815.0,"y":230.0},{"x":594.0,"y":230.0}]},"inferText":"샤르도네","inferConfidence":0.9993,"type":"NORMAL","lineBreak":true},{"valueType":"ALL","boundingPoly":{"vertices":[{"x":867.0,"y":209.0},{"x":930.0,"y":209.0},{"x":930.0,"y":263.0},{"x":867.0,"y":263.0}]},"inferText":"\"","inferConfidence":0.9911,"type":"NORMAL","lineBreak":true},{"valueType":"ALL","boundingPoly":{"vertices":[{"x":480.0,"y":324.0},{"x":594.0,"y":324.0},{"x":594.0,"y":359.0},{"x":480.0,"y":359.0}]},"inferText":"White","inferConfidence":1.0,"type":"NORMAL","lineBreak":true},{"valueType":"ALL","boundingPoly":{"vertices":[{"x":433.0,"y":409.0},{"x":515.0,"y":409.0},{"x":515.0,"y":459.0},{"x":433.0,"y":459.0}]},"inferText":"대표","inferConfidence":1.0,"type":"NORMAL","lineBreak":false},{"valueType":"ALL","boundingPoly":{"vertices":[{"x":516.0,"y":409.0},{"x":600.0,"y":409.0},{"x":600.0,"y":459.0},{"x":516.0,"y":459.0}]},"inferText":"맛과","inferConfidence":0.9998,"type":"NORMAL","lineBreak":false},{"valueType":"ALL","boundingPoly":{"vertices":[{"x":599.0,"y":409.0},{"x":646.0,"y":409.0},{"x":646.0,"y":459.0},{"x":599.0,"y":459.0}]},"inferText":"향","inferConfidence":1.0,"type":"NORMAL","lineBreak":true},{"valueType":"ALL","boundingPoly":{"vertices":[{"x":137.0,"y":742.0},{"x":209.0,"y":742.0},{"x":209.0,"y":758.0},{"x":137.0,"y":758.0}]},"inferText":"CLOUDY","inferConfidence":0.9998,"type":"NORMAL","lineBreak":false},{"valueType":"ALL","boundingPoly":{"vertices":[{"x":213.0,"y":742.0},{"x":246.0,"y":742.0},{"x":246.0,"y":758.0},{"x":213.0,"y":758.0}]},"inferText":"BAY","inferConfidence":0.9992,"type":"NORMAL","lineBreak":true},{"valueType":"ALL","boundingPoly":{"vertices":[{"x":352.0,"y":774.0},{"x":409.0,"y":774.0},{"x":409.0,"y":808.0},{"x":352.0,"y":808.0}]},"inferText":"골드","inferConfidence":1.0,"type":"NORMAL","lineBreak":false},{"valueType":"ALL","boundingPoly":{"vertices":[{"x":412.0,"y":774.0},{"x":494.0,"y":774.0},{"x":494.0,"y":808.0},{"x":412.0,"y":808.0}]},"inferText":"컬러로","inferConfidence":1.0,"type":"NORMAL","lineBreak":false},{"valueType":"ALL","boundingPoly":{"vertices":[{"x":496.0,"y":774.0},{"x":581.0,"y":774.0},{"x":581.0,"y":808.0},{"x":496.0,"y":808.0}]},"inferText":"상쾌한","inferConfidence":1.0,"type":"NORMAL","lineBreak":false},{"valueType":"ALL","boundingPoly":{"vertices":[{"x":583.0,"y":775.0},{"x":622.0,"y":775.0},{"x":622.0,"y":806.0},{"x":583.0,"y":806.0}]},"inferText":"배,","inferConfidence":0.9998,"type":"NORMAL","lineBreak":false},{"valueType":"ALL","boundingPoly":{"vertices":[{"x":624.0,"y":772.0},{"x":714.0,"y":772.0},{"x":714.0,"y":808.0},{"x":624.0,"y":808.0}]},"inferText":"복숭아,","inferConfidence":1.0,"type":"NORMAL","lineBreak":false},{"valueType":"ALL","boundingPoly":{"vertices":[{"x":717.0,"y":774.0},{"x":799.0,"y":774.0},{"x":799.0,"y":808.0},{"x":717.0,"y":808.0}]},"inferText":"프랄린","inferConfidence":0.9995,"type":"NORMAL","lineBreak":false},{"valueType":"ALL","boundingPoly":{"vertices":[{"x":803.0,"y":774.0},{"x":859.0,"y":774.0},{"x":859.0,"y":808.0},{"x":803.0,"y":808.0}]},"inferText":"향이","inferConfidence":0.9999,"type":"NORMAL","lineBreak":false},{"valueType":"ALL","boundingPoly":{"vertices":[{"x":862.0,"y":772.0},{"x":971.0,"y":772.0},{"x":971.0,"y":808.0},{"x":862.0,"y":808.0}]},"inferText":"느껴지며","inferConfidence":1.0,"type":"NORMAL","lineBreak":true},{"valueType":"ALL","boundingPoly":{"vertices":[{"x":352.0,"y":815.0},{"x":459.0,"y":815.0},{"x":459.0,"y":850.0},{"x":352.0,"y":850.0}]},"inferText":"감귤류와","inferConfidence":1.0,"type":"NORMAL","lineBreak":false},{"valueType":"ALL","boundingPoly":{"vertices":[{"x":461.0,"y":815.0},{"x":550.0,"y":815.0},{"x":550.0,"y":850.0},{"x":461.0,"y":850.0}]},"inferText":"복숭아,","inferConfidence":1.0,"type":"NORMAL","lineBreak":false},{"valueType":"ALL","boundingPoly":{"vertices":[{"x":550.0,"y":815.0},{"x":631.0,"y":815.0},{"x":631.0,"y":850.0},{"x":550.0,"y":850.0}]},"inferText":"매실의","inferConfidence":0.9992,"type":"NORMAL","lineBreak":false},{"valueType":"ALL","boundingPoly":{"vertices":[{"x":633.0,"y":817.0},{"x":697.0,"y":817.0},{"x":697.0,"y":850.0},{"x":633.0,"y":850.0}]},"inferText":"풍미,","inferConfidence":1.0,"type":"NORMAL","lineBreak":false},{"valueType":"ALL","boundingPoly":{"vertices":[{"x":697.0,"y":815.0},{"x":781.0,"y":815.0},{"x":781.0,"y":850.0},{"x":697.0,"y":850.0}]},"inferText":"향긋한","inferConfidence":1.0,"type":"NORMAL","lineBreak":false},{"valueType":"ALL","boundingPoly":{"vertices":[{"x":781.0,"y":815.0},{"x":890.0,"y":815.0},{"x":890.0,"y":850.0},{"x":781.0,"y":850.0}]},"inferText":"견과류와","inferConfidence":0.9996,"type":"NORMAL","lineBreak":false},{"valueType":"ALL","boundingPoly":{"vertices":[{"x":892.0,"y":815.0},{"x":973.0,"y":815.0},{"x":973.0,"y":850.0},{"x":892.0,"y":850.0}]},"inferText":"미묘한","inferConfidence":0.9996,"type":"NORMAL","lineBreak":true},{"valueType":"ALL","boundingPoly":{"vertices":[{"x":352.0,"y":858.0},{"x":406.0,"y":858.0},{"x":406.0,"y":889.0},{"x":352.0,"y":889.0}]},"inferText":"오크","inferConfidence":1.0,"type":"NORMAL","lineBreak":false},{"valueType":"ALL","boundingPoly":{"vertices":[{"x":409.0,"y":858.0},{"x":490.0,"y":858.0},{"x":490.0,"y":890.0},{"x":409.0,"y":890.0}]},"inferText":"그리고","inferConfidence":1.0,"type":"NORMAL","lineBreak":false},{"valueType":"ALL","boundingPoly":{"vertices":[{"x":491.0,"y":858.0},{"x":574.0,"y":858.0},{"x":574.0,"y":892.0},{"x":491.0,"y":892.0}]},"inferText":"산뜻한","inferConfidence":0.9993,"type":"NORMAL","lineBreak":false},{"valueType":"ALL","boundingPoly":{"vertices":[{"x":574.0,"y":856.0},{"x":658.0,"y":856.0},{"x":658.0,"y":892.0},{"x":574.0,"y":892.0}]},"inferText":"산미가","inferConfidence":0.9998,"type":"NORMAL","lineBreak":false},{"valueType":"ALL","boundingPoly":{"vertices":[{"x":656.0,"y":856.0},{"x":765.0,"y":856.0},{"x":765.0,"y":892.0},{"x":656.0,"y":892.0}]},"inferText":"피니쉬를","inferConfidence":1.0,"type":"NORMAL","lineBreak":false},{"valueType":"ALL","boundingPoly":{"vertices":[{"x":765.0,"y":859.0},{"x":796.0,"y":859.0},{"x":796.0,"y":890.0},{"x":765.0,"y":890.0}]},"inferText":"꽉","inferConfidence":1.0,"type":"NORMAL","lineBreak":false},{"valueType":"ALL","boundingPoly":{"vertices":[{"x":796.0,"y":856.0},{"x":936.0,"y":856.0},{"x":936.0,"y":892.0},{"x":796.0,"y":892.0}]},"inferText":"잡아줍니다.","inferConfidence":1.0,"type":"NORMAL","lineBreak":true},{"valueType":"ALL","boundingPoly":{"vertices":[{"x":159.0,"y":881.0},{"x":221.0,"y":884.0},{"x":221.0,"y":896.0},{"x":158.0,"y":893.0}]},"inferText":"Chardonnay","inferConfidence":0.9929,"type":"NORMAL","lineBreak":true},{"valueType":"ALL","boundingPoly":{"vertices":[{"x":481.0,"y":1124.0},{"x":599.0,"y":1124.0},{"x":599.0,"y":1174.0},{"x":481.0,"y":1174.0}]},"inferText":"핸들링","inferConfidence":1.0,"type":"NORMAL","lineBreak":true},{"valueType":"ALL","boundingPoly":{"vertices":[{"x":150.0,"y":1439.0},{"x":234.0,"y":1439.0},{"x":234.0,"y":1467.0},{"x":150.0,"y":1467.0}]},"inferText":"적정온도","inferConfidence":1.0,"type":"NORMAL","lineBreak":false},{"valueType":"ALL","boundingPoly":{"vertices":[{"x":508.0,"y":1439.0},{"x":572.0,"y":1439.0},{"x":572.0,"y":1467.0},{"x":508.0,"y":1467.0}]},"inferText":"와인잔","inferConfidence":1.0,"type":"NORMAL","lineBreak":false},{"valueType":"ALL","boundingPoly":{"vertices":[{"x":858.0,"y":1441.0},{"x":920.0,"y":1441.0},{"x":920.0,"y":1467.0},{"x":858.0,"y":1467.0}]},"inferText":"디캔팅","inferConfidence":0.9376,"type":"NORMAL","lineBreak":true},{"valueType":"ALL","boundingPoly":{"vertices":[{"x":131.0,"y":1474.0},{"x":253.0,"y":1474.0},{"x":253.0,"y":1511.0},{"x":131.0,"y":1511.0}]},"inferText":"10-12°C","inferConfidence":0.9999,"type":"NORMAL","lineBreak":false},{"valueType":"ALL","boundingPoly":{"vertices":[{"x":484.0,"y":1470.0},{"x":593.0,"y":1470.0},{"x":593.0,"y":1516.0},{"x":484.0,"y":1516.0}]},"inferText":"화이트","inferConfidence":0.9998,"type":"NORMAL","lineBreak":false},{"valueType":"ALL","boundingPoly":{"vertices":[{"x":862.0,"y":1476.0},{"x":915.0,"y":1476.0},{"x":915.0,"y":1510.0},{"x":862.0,"y":1510.0}]},"inferText":"NO","inferConfidence":0.9994,"type":"NORMAL","lineBreak":true}]}]}